<Properties StartupConfiguration="{BF9F3312-AA39-44DB-A747-2F9097E6813C}|Default">
  <MonoDevelop.Ide.Workbench ActiveDocument="Interview/Services/Implementation/BalanceSheetService.cs">
    <Files>
      <File FileName="Interview.Tests/Unit/BalanceSheetsServiceTests.cs" Line="123" Column="6" />
      <File FileName="Interview/Services/Implementation/BalanceSheetService.cs" Line="25" Column="62" />
      <File FileName="Interview/Models/BalanceSheet.cs" Line="47" Column="40" />
      <File FileName="Interview.Tests/Unit/HelperObjects/MockBalanceSheetStore.cs" Line="22" Column="34" />
      <File FileName="Interview.Tests/Unit/LineItemTests.cs" Line="27" Column="36" />
      <File FileName="Interview.Tests/Unit/HelperObjects/TestBalanceSheet_Unbalanced.cs" Line="10" Column="46" />
      <File FileName="Interview/Services/IBalanceSheetStore.cs" Line="21" Column="30" />
      <File FileName="Interview/Services/Implementation/Logger.cs" Line="16" Column="1" />
      <File FileName="Interview/Models/LineItem.cs" Line="88" Column="66" />
    </Files>
    <Pads>
      <Pad Id="ProjectPad">
        <State name="__root__">
          <Node name="Interview" expanded="True">
            <Node name="Solution Items" expanded="True" />
            <Node name="Interview" expanded="True">
              <Node name="Models" expanded="True" />
              <Node name="Services" expanded="True">
                <Node name="Implementation" expanded="True">
                  <Node name="BalanceSheetService.cs" selected="True" />
                </Node>
              </Node>
            </Node>
            <Node name="Interview.Api" expanded="True">
              <Node name="Properties" expanded="True" />
            </Node>
            <Node name="Interview.Tests" expanded="True">
              <Node name="Dependencies" expanded="True" />
              <Node name="Unit" expanded="True" />
            </Node>
          </Node>
        </State>
      </Pad>
      <Pad Id="MonoDevelop.Debugger.WatchPad">
        <State />
      </Pad>
      <Pad Id="MonoDevelop.UnitTesting.TestPad">
        <State name="__root__">
          <Node name="Interview" expanded="True">
            <Node name="Interview.Tests" expanded="True">
              <Node name="Interview" expanded="True">
                <Node name="Tests" expanded="True">
                  <Node name="Unit" expanded="True">
                    <Node name="BalanceSheetsServiceTests" expanded="True">
                      <Node name="BalanceSheetsService_CanReadLineItemAmount_DoesNotExist" selected="True" />
                    </Node>
                    <Node name="LineItemTests" expanded="True" />
                  </Node>
                </Node>
              </Node>
            </Node>
          </Node>
        </State>
      </Pad>
    </Pads>
  </MonoDevelop.Ide.Workbench>
  <MonoDevelop.Ide.ItemProperties.Interview.Api PreferredExecutionTarget="MonoDevelop.Default" />
  <MonoDevelop.Ide.DebuggingService.PinnedWatches />
  <MonoDevelop.Ide.Workspace ActiveConfiguration="Debug" />
  <MonoDevelop.Ide.DebuggingService.Breakpoints>
    <BreakpointStore />
  </MonoDevelop.Ide.DebuggingService.Breakpoints>
  <MultiItemStartupConfigurations />
</Properties>